mux/mux2x1_dataflow.v
`ifndef MUX2X1_DATAFLOW_V
`define MUX2X1_DATAFLOW_V

module mux2x1 (
    input wire in0,
    input wire in1,
    input wire sel,
    output wire F
);
    
    //dataflow
    assign F = in0&~sel | in1&sel;

endmodule

`endif

mux/testbench.v
`include "mux2x1_dataflow.v"
`timescale 1s/100ms

module testbench;

    reg a, b, s;
    wire F;
    integer i;

    mux2x1 mux2x1_unit(a, b, s, F);

    initial begin
        $dumpfile("sim_mux2x1.vcd");
        $dumpvars(0, testbench);
        for(i = 0;i < 8;i = i+1) begin
            {s, a, b} = i;
            #1;
        end
        $finish;
    end

endmodule

mux/sim_mux2x1.vcd
$date
	Fri Aug 25 13:46:53 2023
$end
$version
	Icarus Verilog
$end
$timescale
	100ms
$end
$scope module testbench $end
$var wire 1 ! F $end
$var reg 1 " a $end
$var reg 1 # b $end
$var reg 1 $ s $end
$var integer 32 % i [31:0] $end
$scope module mux2x1_unit $end
$var wire 1 ! F $end
$var wire 1 " in0 $end
$var wire 1 # in1 $end
$var wire 1 $ sel $end
$upscope $end
$upscope $end
$enddefinitions $end
$comment Show the parameter values. $end
$dumpall
$end
#0
$dumpvars
b0 %
0$
0#
0"
0!
$end
#10
1#
b1 %
#20
1!
1"
0#
b10 %
#30
1#
b11 %
#40
0!
1$
0"
0#
b100 %
#50
1!
1#
b101 %
#60
0!
1"
0#
b110 %
#70
1!
1#
b111 %
#80
b1000 %
